node_hermes_canopen/device/__init__.py
node_hermes_canopen/device/canopen_entries.py
node_hermes_canopen/device/connection_manager.py
node_hermes_canopen/device/device.py
node_hermes_canopen/device/generic.py
node_hermes_canopen/device/mock_device.py
node_hermes_canopen/device/node.py
node_hermes_canopen/network/__init__.py
node_hermes_canopen/network/generic_node.py
node_hermes_canopen/network/kvaeser_node.py
node_hermes_canopen/network/linux_node.py
node_hermes_canopen/network/ui/interface.py
node_hermes_canopen/network/ui/interface.ui
node_hermes_canopen/network/universal_interface.py
node_hermes_canopen/network/universal_node.py
node_hermes_canopen/network/usb2can_node.py
node_hermes_canopen-0.9.0.dist-info/METADATA
node_hermes_canopen-0.9.0.dist-info/WHEEL
node_hermes_canopen-0.9.0.dist-info/RECORD
